firefox_newuser/__init__.py
firefox_newuser/core.py
firefox_newuser/locale/en/LC_MESSAGES/firefox_newuser.mo
firefox_newuser/locale/en.po
firefox_newuser/locale/es/LC_MESSAGES/firefox_newuser.mo
firefox_newuser/locale/es.po
firefox_newuser/locale/firefox_newuser.pot
firefox_newuser/poethepoet.py
firefox_newuser-0.9.0.dist-info/LICENSE.txt
firefox_newuser-0.9.0.dist-info/METADATA
firefox_newuser-0.9.0.dist-info/WHEEL
firefox_newuser-0.9.0.dist-info/entry_points.txt
firefox_newuser-0.9.0.dist-info/RECORD
