Metadata-Version: 2.1
Name: firefox-newuser
Version: 0.9.0
Summary: Script to execute a firefox instance with a recently created user. It deletes user after firefox execution
License: GPL-3.0 license
Author: turulomio
Author-email: turulomio@yahoo.es
Requires-Python: >=3.11,<4.0
Classifier: License :: Other/Proprietary License
Classifier: Programming Language :: Python :: 3
Classifier: Programming Language :: Python :: 3.11
Requires-Dist: colorama (>=0.4.6,<0.5.0)
Requires-Dist: psutil (>=5.9.5,<6.0.0)
Requires-Dist: tqdm (>=4.66.0,<5.0.0)
